{
    "alarm": 61697,
    "archive-book": 61698,
    "archive": 61699,
    "bill": 61700,
    "card-add": 61701,
    "card-edit": 61702,
    "card-pos": 61703,
    "card-receive": 61704,
    "card-remove-2": 61705,
    "card-remove": 61706,
    "card-send": 61707,
    "card-slash": 61708,
    "card-tick-2": 61709,
    "card-tick": 61710,
    "card": 61711,
    "cards": 61712,
    "chart-square": 61713,
    "check": 61714,
    "clipboard-close": 61715,
    "clipboard-export": 61716,
    "clipboard-import": 61717,
    "clipboard-text": 61718,
    "clipboard-tick": 61719,
    "code-2": 61720,
    "code-circle": 61721,
    "code": 61722,
    "coin-2": 61723,
    "coin": 61724,
    "command-square": 61725,
    "command": 61726,
    "convert-card": 61727,
    "copyright": 61728,
    "creative-commons": 61729,
    "data-2": 61730,
    "data": 61731,
    "discount-circle": 61732,
    "discount-shape": 61733,
    "document-2": 61734,
    "document-cloud": 61735,
    "document-code-2": 61736,
    "document-code": 61737,
    "document-copy": 61738,
    "document-download": 61739,
    "document-favorite": 61740,
    "document-filter": 61741,
    "document-forward": 61742,
    "document-like": 61743,
    "document-normal": 61744,
    "document-previous": 61745,
    "document-sketch": 61746,
    "document-text-2": 61747,
    "document-text": 61748,
    "document-upload": 61749,
    "document": 61750,
    "dollar-circle": 61751,
    "dollar-square": 61752,
    "edit-2": 61753,
    "edit": 61754,
    "empty-wallet-add": 61755,
    "empty-wallet-change": 61756,
    "empty-wallet-remove": 61757,
    "empty-wallet-tick": 61758,
    "empty-wallet-time": 61759,
    "empty-wallet": 61760,
    "eye-slash": 61761,
    "eye": 61762,
    "finger-cricle": 61763,
    "finger-scan": 61764,
    "frame": 61765,
    "hashtag-down": 61766,
    "hashtag-up": 61767,
    "hashtag": 61768,
    "hierarchy-2": 61769,
    "hierarchy-3": 61770,
    "hierarchy-square-2": 61771,
    "hierarchy-square-3": 61772,
    "hierarchy-square": 61773,
    "hierarchy": 61774,
    "key-square": 61775,
    "key": 61776,
    "lock-2": 61777,
    "lock-circle": 61778,
    "lock-slash": 61779,
    "lock": 61780,
    "math": 61781,
    "menu-board": 61782,
    "message-programming": 61783,
    "mobile-programming": 61784,
    "money-2": 61785,
    "money-3": 61786,
    "money-4": 61787,
    "money-add": 61788,
    "money-change": 61789,
    "money-forbidden": 61790,
    "money-recive": 61791,
    "money-remove": 61792,
    "money-send": 61793,
    "money-tick": 61794,
    "money-time": 61795,
    "money": 61796,
    "moneys": 61797,
    "note-2": 61798,
    "note-add": 61799,
    "note-favorite": 61800,
    "note-remove": 61801,
    "note-text": 61802,
    "note": 61803,
    "password-check": 61804,
    "percentage-circle": 61805,
    "percentage-square": 61806,
    "programming-arrow": 61807,
    "programming-arrows": 61808,
    "radar": 61809,
    "receipt-2": 61810,
    "receipt-3": 61811,
    "receipt-4": 61812,
    "receipt-add": 61813,
    "receipt-discount": 61814,
    "receipt-disscount": 61815,
    "receipt-edit": 61816,
    "receipt-item": 61817,
    "receipt-minus": 61818,
    "receipt-search": 61819,
    "receipt-text": 61820,
    "receipt": 61821,
    "scan-barcode": 61822,
    "scan": 61823,
    "scanner": 61824,
    "scanning": 61825,
    "scroll": 61826,
    "security-card": 61827,
    "security-safe": 61828,
    "security-user": 61829,
    "security": 61830,
    "shield-cross": 61831,
    "shield-search": 61832,
    "shield-slash": 61833,
    "shield-tick": 61834,
    "shield": 61835,
    "sidebar-bottom": 61836,
    "sidebar-left": 61837,
    "sidebar-right": 61838,
    "sidebar-top": 61839,
    "stickynote": 61840,
    "strongbox-2": 61841,
    "strongbox": 61842,
    "tag-2": 61843,
    "tag": 61844,
    "task-square": 61845,
    "task": 61846,
    "ticket-2": 61847,
    "ticket-discount": 61848,
    "ticket-expired": 61849,
    "ticket-star": 61850,
    "ticket": 61851,
    "transaction-minus": 61852,
    "unlock": 61853,
    "wallet-2": 61854,
    "wallet-3": 61855,
    "wallet-4": 61856,
    "wallet-add-2": 61857,
    "wallet-add": 61858,
    "wallet-check": 61859,
    "wallet-money": 61860,
    "wallet-remove": 61861,
    "wallet-search": 61862,
    "wallet": 61863
}